fleming/__init__.py
fleming/code_summary/__init__.py
fleming/code_summary/fourO_mini_summary.py
fleming/code_summary/repo_contents_tokenisation.py
fleming/discovery/__init__.py
fleming/discovery/corpus_creation.py
fleming/discovery/model_query.py
fleming/discovery/model_serve.py
fleming/discovery/model_train_register.py
project_fleming-0.0.4.dist-info/LICENSE.md
project_fleming-0.0.4.dist-info/METADATA
project_fleming-0.0.4.dist-info/WHEEL
project_fleming-0.0.4.dist-info/top_level.txt
project_fleming-0.0.4.dist-info/RECORD
